main.py
ruff_report-0.0.1.dist-info/licenses/LICENSE
ruff_report-0.0.1.dist-info/METADATA
ruff_report-0.0.1.dist-info/WHEEL
ruff_report-0.0.1.dist-info/top_level.txt
ruff_report-0.0.1.dist-info/RECORD
