Metadata-Version: 2.4
Name: ruff-report
Version: 0.0.1
Summary: Tool to generate a beautiful report based on ruff lintingse
License-Expression: MIT
Requires-Python: >=3.13
License-File: LICENSE
Dynamic: license-file
